uma_crypto/__init__.py
uma_crypto/libuniffi_uma_crypto.dylib
uma_crypto/uma_crypto.py
uma_crypto_python-0.1.0.dist-info/LICENSE
uma_crypto_python-0.1.0.dist-info/METADATA
uma_crypto_python-0.1.0.dist-info/WHEEL
uma_crypto_python-0.1.0.dist-info/top_level.txt
uma_crypto_python-0.1.0.dist-info/RECORD
