Metadata-Version: 2.1
Name: uma-crypto-python
Version: 0.1.0
Summary: The Python language bindings for UMA crypto operations
Home-page: https://github.com/uma-universal-money-address/uma-crypto-uniffi
Author: Lightspark Group, Inc. <info@lightspark.com>
License: Apache 2.0
License-File: LICENSE
